MANIFEST.in
README.md
README.rst
setup.py
bin/viewmydb
viewmydb/DBcreatetable.py
viewmydb/DBstructure.py
viewmydb/TableBrowse.py
viewmydb/TableDrop.py
viewmydb/TableEdit.py
viewmydb/TableStructure.py
viewmydb/TableTruncate.py
viewmydb/__init__.py
viewmydb/loginview.py
viewmydb/mainview.py
viewmydb/mysqlDB.py
viewmydb/psqlDB.py
viewmydb/runsql.py
viewmydb/start.py
viewmydb.egg-info/PKG-INFO
viewmydb.egg-info/SOURCES.txt
viewmydb.egg-info/dependency_links.txt
viewmydb.egg-info/not-zip-safe
viewmydb.egg-info/requires.txt
viewmydb.egg-info/top_level.txt