Metadata-Version: 1.1
Name: viewmydb
Version: 0.1.5
Summary: Python terminal GUI for MySQL and PostgreSQL DBs.
Home-page: http://github.com/OSU-CS419/viewmydb
Author: reformingpanda, davidtadams
Author-email: adams.t.david@gmail.com
License: MIT
Keywords: mysql,postgresql,urwid,ncurses,curses
Platform: UNKNOWN
Classifier: Development Status :: 4 - Beta
Classifier: Environment :: Console :: Curses
Classifier: Programming Language :: Python :: 2.7
Classifier: Intended Audience :: Information Technology
Classifier: Natural Language :: English
Classifier: License :: OSI Approved :: MIT License
Classifier: Operating System :: POSIX :: Linux
Classifier: Topic :: Database :: Front-Ends
